MANIFEST.in
setup.py
Products/__init__.py
Products.SilvaPoll.egg-info/PKG-INFO
Products.SilvaPoll.egg-info/SOURCES.txt
Products.SilvaPoll.egg-info/dependency_links.txt
Products.SilvaPoll.egg-info/namespace_packages.txt
Products.SilvaPoll.egg-info/not-zip-safe
Products.SilvaPoll.egg-info/requires.txt
Products.SilvaPoll.egg-info/top_level.txt
Products/SilvaPoll/CREDITS.txt
Products/SilvaPoll/HISTORY.txt
Products/SilvaPoll/PollQuestion.png
Products/SilvaPoll/PollQuestion.py
Products/SilvaPoll/README.txt
Products/SilvaPoll/ServicePolls.png
Products/SilvaPoll/ServicePolls.py
Products/SilvaPoll/ServicePollsMySQL.py
Products/SilvaPoll/__init__.py
Products/SilvaPoll/configure.zcml
Products/SilvaPoll/cs_configuration_form.form
Products/SilvaPoll/ftesting.zcml
Products/SilvaPoll/interfaces.py
Products/SilvaPoll/smi.py
Products/SilvaPoll/sqldb.py
Products/SilvaPoll/testing.py
Products/SilvaPoll/zodbdb.py
Products/SilvaPoll/PollQuestion_templates/pollquestionview.cpt
Products/SilvaPoll/i18n/__init__.py
Products/SilvaPoll/i18n/silva_poll.pot
Products/SilvaPoll/i18n/de/LC_MESSAGES/silva_poll.mo
Products/SilvaPoll/i18n/de/LC_MESSAGES/silva_poll.po
Products/SilvaPoll/i18n/en/LC_MESSAGES/silva_poll.mo
Products/SilvaPoll/i18n/en/LC_MESSAGES/silva_poll.po
Products/SilvaPoll/smi_templates/questioninfo.cpt
Products/SilvaPoll/static/poll.css
Products/SilvaPoll/tests/__init__.py
Products/SilvaPoll/tests/test_questions.py
Products/SilvaPoll/tests/test_service.py