Metadata-Version: 1.1
Name: Products.SilvaPoll
Version: 3.0
Summary: Poll extension for Silva CMS
Home-page: https://github.com/silvacms/Products.SilvaPoll
Author: Guido Wesdorp, Wim Boucquaert, Jasper Op De Coul
Author-email: info@infrae.com
License: BSD
Keywords: poll silva zope2
Platform: UNKNOWN
Classifier: Framework :: Zope2
Classifier: License :: OSI Approved :: BSD License
Classifier: Programming Language :: Python
Classifier: Topic :: Software Development :: Libraries :: Python Modules
